pyfitness/__init__.py
pyfitness/dynamics.py
pyfitness/fd_loader.py
pyfitness/sdk_loader.py
pyfitness/statistics.py
pyfitness-2025.4.0.dist-info/licenses/LICENSE
pyfitness-2025.4.0.dist-info/METADATA
pyfitness-2025.4.0.dist-info/WHEEL
pyfitness-2025.4.0.dist-info/top_level.txt
pyfitness-2025.4.0.dist-info/RECORD
